clickup-priorities/__init__.py
clickup-priorities/funciones.py
clickup_priorities/__init__.py
clickup_priorities/funciones.py
clickup_priorities-0.0.7.dist-info/METADATA
clickup_priorities-0.0.7.dist-info/WHEEL
clickup_priorities-0.0.7.dist-info/top_level.txt
clickup_priorities-0.0.7.dist-info/RECORD
