Metadata-Version: 2.1
Name: clickup-priorities
Version: 0.0.7
Summary: sacar las prioridades de una(varias) vista(s) de clickup
Home-page: https://github.com/joseA-carrera
Author: Jose Alveiro Carrera
Author-email: jose2252017@gmail.com
License: MIT
Requires-Dist: requests
